<?xml version="1.0" encoding="GB2312"?>
<goodsExtList>
  <goods>
    <vgno>000232</vgno>
    <barcode>120000000000</barcode>
    <name>叉烧酥</name>
    <deptid>09122213</deptid>
    <spec>大</spec>
    <unit>个</unit>
    <price>350</price>
    <type>0</type>
    <x>1</x>
    <ptype>n</ptype>
    <prodtype>0</prodtype>
    <pknum>1</pknum>
  </goods>
  <goods>
    <vgno>000013</vgno>
    <barcode>123123123123</barcode>
    <name>蛋黄红豆月</name>
    <deptid>01212133</deptid>
    <spec>740g</spec>
    <unit>盒</unit>
    <price>21800</price>
    <type>0</type>
    <x>1</x>
    <ptype>n</ptype>
    <prodtype>0</prodtype>
    <pknum>1</pknum>
  </goods>
  <goods>
    <vgno>000366</vgno>
    <barcode>180000000001</barcode>
    <name>香芹吞拿鱼包</name>
    <deptid>18111111</deptid>
    <spec>100g</spec>
    <unit>个</unit>
    <price>350</price>
    <type>0</type>
    <x>1</x>
    <ptype>n</ptype>
    <prodtype>0</prodtype>
    <pknum>1</pknum>
  </goods>
  <goods>
    <vgno>000367</vgno>
    <barcode>180000000002</barcode>
    <name>至尊意式薄饼</name>
    <deptid>18111111</deptid>
    <spec>100g</spec>
    <unit>个</unit>
    <price>600</price>
    <type>0</type>
    <x>1</x>
    <ptype>n</ptype>
    <prodtype>0</prodtype>
    <pknum>1</pknum>
  </goods>
  <goods>
    <vgno>000368</vgno>
    <barcode>180000000003</barcode>
    <name>泰汁串烧包</name>
    <deptid>18111111</deptid>
    <spec>100g</spec>
    <unit>个</unit>
    <price>800</price>
    <type>0</type>
    <x>1</x>
    <ptype>n</ptype>
    <prodtype>0</prodtype>
    <pknum>1</pknum>
  </goods>
  <goods>
    <vgno>000369</vgno>
    <barcode>180000000004</barcode>
    <name>芝士脆肠包</name>
    <deptid>18111111</deptid>
    <spec>100g</spec>
    <unit>个</unit>
    <price>600</price>
    <type>0</type>
    <x>1</x>
    <ptype>n</ptype>
    <prodtype>0</prodtype>
    <pknum>1</pknum>
  </goods>
  <goods>
    <vgno>000407</vgno>
    <barcode>1800000000043</barcode>
    <name>烟肉丹麦包</name>
    <deptid>18111111</deptid>
    <spec>大</spec>
    <unit>个</unit>
    <price>600</price>
    <type>0</type>
    <x>1</x>
    <ptype>n</ptype>
    <prodtype>0</prodtype>
    <pknum>1</pknum>
  </goods>
  <goods>
    <vgno>000370</vgno>
    <barcode>180000000005</barcode>
    <name>香蒜虾仁包</name>
    <deptid>18111111</deptid>
    <spec>100g</spec>
    <unit>个</unit>
    <price>500</price>
    <type>0</type>
    <x>1</x>
    <ptype>n</ptype>
    <prodtype>0</prodtype>
    <pknum>1</pknum>
  </goods>
  <goods>
    <vgno>000371</vgno>
    <barcode>180000000006</barcode>
    <name>餐蛋肉松包</name>
    <deptid>18111111</deptid>
    <spec>85g</spec>
    <unit>个</unit>
    <price>500</price>
    <type>0</type>
    <x>1</x>
    <ptype>n</ptype>
    <prodtype>0</prodtype>
    <pknum>1</pknum>
  </goods>
  <goods>
    <vgno>000372</vgno>
    <barcode>180000000007</barcode>
    <name>烧汁肠仔包</name>
    <deptid>18111111</deptid>
    <spec>85g</spec>
    <unit>个</unit>
    <price>350</price>
    <type>0</type>
    <x>1</x>
    <ptype>n</ptype>
    <prodtype>0</prodtype>
    <pknum>1</pknum>
  </goods>
  <goods>
    <vgno>000373</vgno>
    <barcode>180000000008</barcode>
    <name>栗子包</name>
    <deptid>18111111</deptid>
    <spec>85g</spec>
    <unit>个</unit>
    <price>350</price>
    <type>0</type>
    <x>1</x>
    <ptype>n</ptype>
    <prodtype>0</prodtype>
    <pknum>1</pknum>
  </goods>
  <goods>
    <vgno>000374</vgno>
    <barcode>180000000009</barcode>
    <name>白汁鸡肉包</name>
    <deptid>18111111</deptid>
    <spec>85g</spec>
    <unit>个</unit>
    <price>300</price>
    <type>0</type>
    <x>1</x>
    <ptype>n</ptype>
    <prodtype>0</prodtype>
    <pknum>1</pknum>
  </goods>
  <goods>
    <vgno>000375</vgno>
    <barcode>180000000010</barcode>
    <name>叉烧包</name>
    <deptid>18111111</deptid>
    <spec>85g</spec>
    <unit>个</unit>
    <price>450</price>
    <type>0</type>
    <x>1</x>
    <ptype>n</ptype>
    <prodtype>0</prodtype>
    <pknum>1</pknum>
  </goods>
  <goods>
    <vgno>000376</vgno>
    <barcode>180000000011</barcode>
    <name>肉松包</name>
    <deptid>18111111</deptid>
    <spec>85g</spec>
    <unit>个</unit>
    <price>400</price>
    <type>0</type>
    <x>1</x>
    <ptype>n</ptype>
    <prodtype>0</prodtype>
    <pknum>1</pknum>
  </goods>
  <goods>
    <vgno>000377</vgno>
    <barcode>180000000012</barcode>
    <name>芝士烟肉包</name>
    <deptid>18111111</deptid>
    <spec>85g</spec>
    <unit>个</unit>
    <price>350</price>
    <type>0</type>
    <x>1</x>
    <ptype>n</ptype>
    <prodtype>0</prodtype>
    <pknum>1</pknum>
  </goods>
  <goods>
    <vgno>000378</vgno>
    <barcode>180000000013</barcode>
    <name>?宝脆肠</name>
    <deptid>18111111</deptid>
    <spec>85g</spec>
    <unit>个</unit>
    <price>350</price>
    <type>0</type>
    <x>1</x>
    <ptype>n</ptype>
    <prodtype>0</prodtype>
    <pknum>1</pknum>
  </goods>
  <goods>
    <vgno>000379</vgno>
    <barcode>180000000014</barcode>
    <name>黄金瓜子包</name>
    <deptid>18111111</deptid>
    <spec>85g</spec>
    <unit>个</unit>
    <price>350</price>
    <type>0</type>
    <x>1</x>
    <ptype>n</ptype>
    <prodtype>0</prodtype>
    <pknum>1</pknum>
  </goods>
  <goods>
    <vgno>000381</vgno>
    <barcode>180000000015</barcode>
    <name>葡汁肉碎海苔包</name>
    <deptid>18111111</deptid>
    <spec>85g</spec>
    <unit>个</unit>
    <price>350</price>
    <type>0</type>
    <x>1</x>
    <ptype>n</ptype>
    <prodtype>0</prodtype>
    <pknum>1</pknum>
  </goods>
  <goods>
    <vgno>000380</vgno>
    <barcode>180000000016</barcode>
    <name>蒜蓉法包</name>
    <deptid>18111111</deptid>
    <spec>85g</spec>
    <unit>个</unit>
    <price>400</price>
    <type>0</type>
    <x>1</x>
    <ptype>n</ptype>
    <prodtype>0</prodtype>
    <pknum>1</pknum>
  </goods>
  <goods>
    <vgno>000382</vgno>
    <barcode>180000000017</barcode>
    <name>菠萝粒粒红豆包</name>
    <deptid>18111111</deptid>
    <spec>85g</spec>
    <unit>个</unit>
    <price>300</price>
    <type>0</type>
    <x>1</x>
    <ptype>n</ptype>
    <prodtype>0</prodtype>
    <pknum>1</pknum>
  </goods>
  <goods>
    <vgno>000384</vgno>
    <barcode>180000000019</barcode>
    <name>鲜奶忌廉</name>
    <deptid>18111111</deptid>
    <spec>85g</spec>
    <unit>个</unit>
    <price>350</price>
    <type>0</type>
    <x>1</x>
    <ptype>n</ptype>
    <prodtype>0</prodtype>
    <pknum>1</pknum>
  </goods>
  <goods>
    <vgno>000385</vgno>
    <barcode>180000000020</barcode>
    <name>椰子菠萝包</name>
    <deptid>18111111</deptid>
    <spec>85g</spec>
    <unit>个</unit>
    <price>400</price>
    <type>0</type>
    <x>1</x>
    <ptype>n</ptype>
    <prodtype>0</prodtype>
    <pknum>1</pknum>
  </goods>
  <goods>
    <vgno>000386</vgno>
    <barcode>180000000021</barcode>
    <name>粟米火腿包</name>
    <deptid>18111111</deptid>
    <spec>85g</spec>
    <unit>个</unit>
    <price>400</price>
    <type>0</type>
    <x>1</x>
    <ptype>n</ptype>
    <prodtype>0</prodtype>
    <pknum>1</pknum>
  </goods>
  <goods>
    <vgno>000387</vgno>
    <barcode>180000000022</barcode>
    <name>鲜奶香芋包</name>
    <deptid>18111111</deptid>
    <spec>85g</spec>
    <unit>个</unit>
    <price>400</price>
    <type>0</type>
    <x>1</x>
    <ptype>n</ptype>
    <prodtype>0</prodtype>
    <pknum>1</pknum>
  </goods>
  <goods>
    <vgno>000388</vgno>
    <barcode>180000000023</barcode>
    <name>沙茶牛肉包</name>
    <deptid>18111111</deptid>
    <spec>85g</spec>
    <unit>个</unit>
    <price>400</price>
    <type>0</type>
    <x>1</x>
    <ptype>n</ptype>
    <prodtype>0</prodtype>
    <pknum>1</pknum>
  </goods>
  <goods>
    <vgno>000389</vgno>
    <barcode>180000000024</barcode>
    <name>?宝芝士火腿</name>
    <deptid>18111111</deptid>
    <spec>85g</spec>
    <unit>个</unit>
    <price>350</price>
    <type>0</type>
    <x>1</x>
    <ptype>n</ptype>
    <prodtype>0</prodtype>
    <pknum>1</pknum>
  </goods>
  <goods>
    <vgno>000390</vgno>
    <barcode>180000000025</barcode>
    <name>?油鸡包</name>
    <deptid>18111111</deptid>
    <spec>85g</spec>
    <unit>个</unit>
    <price>400</price>
    <type>0</type>
    <x>1</x>
    <ptype>n</ptype>
    <prodtype>0</prodtype>
    <pknum>1</pknum>
  </goods>
  <goods>
    <vgno>000392</vgno>
    <barcode>180000000027</barcode>
    <name>芝麻条</name>
    <deptid>18111111</deptid>
    <spec>65g</spec>
    <unit>个</unit>
    <price>200</price>
    <type>0</type>
    <x>1</x>
    <ptype>n</ptype>
    <prodtype>0</prodtype>
    <pknum>1</pknum>
  </goods>
  <goods>
    <vgno>000393</vgno>
    <barcode>180000000028</barcode>
    <name>蒜香餐包</name>
    <deptid>18111111</deptid>
    <spec>65g</spec>
    <unit>个</unit>
    <price>200</price>
    <type>0</type>
    <x>1</x>
    <ptype>n</ptype>
    <prodtype>0</prodtype>
    <pknum>1</pknum>
  </goods>
  <goods>
    <vgno>000394</vgno>
    <barcode>180000000029</barcode>
    <name>麦芽餐包</name>
    <deptid>18111111</deptid>
    <spec>65g</spec>
    <unit>个</unit>
    <price>200</price>
    <type>0</type>
    <x>1</x>
    <ptype>n</ptype>
    <prodtype>0</prodtype>
    <pknum>1</pknum>
  </goods>
  <goods>
    <vgno>000396</vgno>
    <barcode>180000000031</barcode>
    <name>法包(长包)</name>
    <deptid>18211111</deptid>
    <spec>300g</spec>
    <unit>个</unit>
    <price>1000</price>
    <type>0</type>
    <x>1</x>
    <ptype>n</ptype>
    <prodtype>0</prodtype>
    <pknum>1</pknum>
  </goods>
  <goods>
    <vgno>000397</vgno>
    <barcode>180000000032</barcode>
    <name>核桃法包</name>
    <deptid>18111111</deptid>
    <spec>100g</spec>
    <unit>个</unit>
    <price>400</price>
    <type>0</type>
    <x>1</x>
    <ptype>n</ptype>
    <prodtype>0</prodtype>
    <pknum>1</pknum>
  </goods>
  <goods>
    <vgno>000399</vgno>
    <barcode>180000000034</barcode>
    <name>鸡尾排包</name>
    <deptid>18211111</deptid>
    <spec>大</spec>
    <unit>个</unit>
    <price>750</price>
    <type>0</type>
    <x>1</x>
    <ptype>n</ptype>
    <prodtype>0</prodtype>
    <pknum>1</pknum>
  </goods>
  <goods>
    <vgno>000401</vgno>
    <barcode>180000000036</barcode>
    <name>芝士牛角包</name>
    <deptid>18111111</deptid>
    <spec>40g</spec>
    <unit>个</unit>
    <price>400</price>
    <type>0</type>
    <x>1</x>
    <ptype>n</ptype>
    <prodtype>0</prodtype>
    <pknum>1</pknum>
  </goods>
  <goods>
    <vgno>000402</vgno>
    <barcode>180000000037</barcode>
    <name>樱桃丹麦包</name>
    <deptid>18111111</deptid>
    <spec>大</spec>
    <unit>个</unit>
    <price>600</price>
    <type>0</type>
    <x>1</x>
    <ptype>n</ptype>
    <prodtype>0</prodtype>
    <pknum>1</pknum>
  </goods>
  <goods>
    <vgno>000403</vgno>
    <barcode>180000000038</barcode>
    <name>鲜什果丹麦包</name>
    <deptid>18111111</deptid>
    <spec>大</spec>
    <unit>个</unit>
    <price>400</price>
    <type>0</type>
    <x>1</x>
    <ptype>n</ptype>
    <prodtype>0</prodtype>
    <pknum>1</pknum>
  </goods>
  <goods>
    <vgno>000404</vgno>
    <barcode>180000000039</barcode>
    <name>芒果丹麦包</name>
    <deptid>18111111</deptid>
    <spec>大</spec>
    <unit>个</unit>
    <price>400</price>
    <type>0</type>
    <x>1</x>
    <ptype>n</ptype>
    <prodtype>0</prodtype>
    <pknum>1</pknum>
  </goods>
  <goods>
    <vgno>000405</vgno>
    <barcode>180000000040</barcode>
    <name>草莓丹麦包</name>
    <deptid>18111111</deptid>
    <spec>大</spec>
    <unit>个</unit>
    <price>400</price>
    <type>0</type>
    <x>1</x>
    <ptype>n</ptype>
    <prodtype>0</prodtype>
    <pknum>1</pknum>
  </goods>
  <goods>
    <vgno>000409</vgno>
    <barcode>180000000041</barcode>
    <name>全麦小米</name>
    <deptid>18211111</deptid>
    <spec>150g</spec>
    <unit>个</unit>
    <price>500</price>
    <type>0</type>
    <x>1</x>
    <ptype>n</ptype>
    <prodtype>0</prodtype>
    <pknum>1</pknum>
  </goods>
  <goods>
    <vgno>000406</vgno>
    <barcode>180000000042</barcode>
    <name>咖喱牛肉丹麦包</name>
    <deptid>18111111</deptid>
    <spec>大</spec>
    <unit>个</unit>
    <price>400</price>
    <type>0</type>
    <x>1</x>
    <ptype>n</ptype>
    <prodtype>0</prodtype>
    <pknum>1</pknum>
  </goods>
  <goods>
    <vgno>000408</vgno>
    <barcode>180000000044</barcode>
    <name>低脂燕麦核桃包</name>
    <deptid>19411111</deptid>
    <spec>110g</spec>
    <unit>个</unit>
    <price>600</price>
    <type>0</type>
    <x>1</x>
    <ptype>n</ptype>
    <prodtype>0</prodtype>
    <pknum>1</pknum>
  </goods>
  <goods>
    <vgno>000410</vgno>
    <barcode>180000000045</barcode>
    <name>亚麻籽健康包</name>
    <deptid>18211111</deptid>
    <spec>150g</spec>
    <unit>个</unit>
    <price>500</price>
    <type>0</type>
    <x>1</x>
    <ptype>n</ptype>
    <prodtype>0</prodtype>
    <pknum>1</pknum>
  </goods>
  <goods>
    <vgno>000411</vgno>
    <barcode>180000000047</barcode>
    <name>五谷子包</name>
    <deptid>18211111</deptid>
    <spec>150g</spec>
    <unit>个</unit>
    <price>500</price>
    <type>0</type>
    <x>1</x>
    <ptype>n</ptype>
    <prodtype>0</prodtype>
    <pknum>1</pknum>
  </goods>
  <goods>
    <vgno>000424</vgno>
    <barcode>180000000059</barcode>
    <name>鲜牛奶白方包</name>
    <deptid>18211111</deptid>
    <spec>180g</spec>
    <unit>包</unit>
    <price>300</price>
    <type>0</type>
    <x>1</x>
    <ptype>n</ptype>
    <prodtype>0</prodtype>
    <pknum>1</pknum>
  </goods>
  <goods>
    <vgno>000425</vgno>
    <barcode>180000000060</barcode>
    <name>英式吐司</name>
    <deptid>18211111</deptid>
    <spec>290g</spec>
    <unit>包</unit>
    <price>600</price>
    <type>0</type>
    <x>1</x>
    <ptype>n</ptype>
    <prodtype>0</prodtype>
    <pknum>1</pknum>
  </goods>
  <goods>
    <vgno>000426</vgno>
    <barcode>180000000061</barcode>
    <name>英式全麦吐司</name>
    <deptid>18211111</deptid>
    <spec>240g</spec>
    <unit>包</unit>
    <price>700</price>
    <type>0</type>
    <x>1</x>
    <ptype>n</ptype>
    <prodtype>0</prodtype>
    <pknum>1</pknum>
  </goods>
  <goods>
    <vgno>000427</vgno>
    <barcode>180000000062</barcode>
    <name>鲜牛油排包</name>
    <deptid>18211111</deptid>
    <spec>280g</spec>
    <unit>包</unit>
    <price>850</price>
    <type>0</type>
    <x>1</x>
    <ptype>n</ptype>
    <prodtype>0</prodtype>
    <pknum>1</pknum>
  </goods>
  <goods>
    <vgno>000428</vgno>
    <barcode>180000000063</barcode>
    <name>紫米红豆吐司</name>
    <deptid>18211111</deptid>
    <spec>150g</spec>
    <unit>包</unit>
    <price>400</price>
    <type>0</type>
    <x>1</x>
    <ptype>n</ptype>
    <prodtype>0</prodtype>
    <pknum>1</pknum>
  </goods>
  <goods>
    <vgno>000429</vgno>
    <barcode>180000000064</barcode>
    <name>鲜奶粟米包</name>
    <deptid>18211111</deptid>
    <spec>210g</spec>
    <unit>包</unit>
    <price>800</price>
    <type>0</type>
    <x>1</x>
    <ptype>n</ptype>
    <prodtype>0</prodtype>
    <pknum>1</pknum>
  </goods>
  <goods>
    <vgno>000430</vgno>
    <barcode>180000000065</barcode>
    <name>鲜牛奶餐包</name>
    <deptid>18211111</deptid>
    <spec>170g</spec>
    <unit>包</unit>
    <price>350</price>
    <type>0</type>
    <x>1</x>
    <ptype>n</ptype>
    <prodtype>0</prodtype>
    <pknum>1</pknum>
  </goods>
  <goods>
    <vgno>000431</vgno>
    <barcode>180000000066</barcode>
    <name>香薯芝士包</name>
    <deptid>18211111</deptid>
    <spec>190g</spec>
    <unit>包</unit>
    <price>500</price>
    <type>0</type>
    <x>1</x>
    <ptype>n</ptype>
    <prodtype>0</prodtype>
    <pknum>1</pknum>
  </goods>
  <goods>
    <vgno>000432</vgno>
    <barcode>180000000067</barcode>
    <name>黑麦甜餐包</name>
    <deptid>18211111</deptid>
    <spec>170g</spec>
    <unit>包</unit>
    <price>350</price>
    <type>0</type>
    <x>1</x>
    <ptype>n</ptype>
    <prodtype>0</prodtype>
    <pknum>1</pknum>
  </goods>
  <goods>
    <vgno>000566</vgno>
    <barcode>180000000203</barcode>
    <name>农夫包</name>
    <deptid>18211111</deptid>
    <spec>大</spec>
    <unit>个</unit>
    <price>1000</price>
    <type>0</type>
    <x>1</x>
    <ptype>n</ptype>
    <prodtype>0</prodtype>
    <pknum>1</pknum>
  </goods>
  <goods>
    <vgno>000573</vgno>
    <barcode>180000000210</barcode>
    <name>蓝莓丹麦包</name>
    <deptid>18111111</deptid>
    <spec>大</spec>
    <unit>个</unit>
    <price>400</price>
    <type>0</type>
    <x>1</x>
    <ptype>n</ptype>
    <prodtype>0</prodtype>
    <pknum>1</pknum>
  </goods>
  <goods>
    <vgno>000852</vgno>
    <barcode>180000000267</barcode>
    <name>菠萝椰奶包</name>
    <deptid>18111111</deptid>
    <spec>95g</spec>
    <unit>个</unit>
    <price>300</price>
    <type>0</type>
    <x>1</x>
    <ptype>n</ptype>
    <prodtype>0</prodtype>
    <pknum>1</pknum>
  </goods>
  <goods>
    <vgno>000760</vgno>
    <barcode>2100076000008</barcode>
    <name>雪彩缤纷冰皮月饼</name>
    <deptid>01212133</deptid>
    <spec>620g</spec>
    <unit>盒</unit>
    <price>21800</price>
    <type>0</type>
    <x>1</x>
    <ptype>n</ptype>
    <prodtype>0</prodtype>
    <pknum>1</pknum>
  </goods>
  <goods>
    <vgno>000761</vgno>
    <barcode>2100076100005</barcode>
    <name>雪中情冰皮月饼</name>
    <deptid>01212133</deptid>
    <spec>330g</spec>
    <unit>盒</unit>
    <price>14800</price>
    <type>0</type>
    <x>1</x>
    <ptype>n</ptype>
    <prodtype>0</prodtype>
    <pknum>1</pknum>
  </goods>
  <goods>
    <vgno>000842</vgno>
    <barcode>2100084200001</barcode>
    <name>红豆芝麻扁</name>
    <deptid>18111111</deptid>
    <spec>1</spec>
    <unit>个</unit>
    <price>300</price>
    <type>0</type>
    <x>1</x>
    <ptype>n</ptype>
    <prodtype>0</prodtype>
    <pknum>1</pknum>
  </goods>
  <goods>
    <vgno>001177</vgno>
    <barcode>2100117700003</barcode>
    <name>日式甜心</name>
    <deptid>18111111</deptid>
    <spec />
    <unit>个</unit>
    <price>180</price>
    <type>0</type>
    <x>1</x>
    <ptype>n</ptype>
    <prodtype>0</prodtype>
    <pknum>1</pknum>
  </goods>
  <goods>
    <vgno>001182</vgno>
    <barcode>2100118200007</barcode>
    <name>芝士肉松</name>
    <deptid>18111111</deptid>
    <spec />
    <unit>个</unit>
    <price>450</price>
    <type>0</type>
    <x>1</x>
    <ptype>n</ptype>
    <prodtype>0</prodtype>
    <pknum>1</pknum>
  </goods>
  <goods>
    <vgno>001187</vgno>
    <barcode>2100118700002</barcode>
    <name>菠萝包</name>
    <deptid>18111111</deptid>
    <spec />
    <unit>个</unit>
    <price>180</price>
    <type>0</type>
    <x>1</x>
    <ptype>n</ptype>
    <prodtype>0</prodtype>
    <pknum>1</pknum>
  </goods>
  <goods>
    <vgno>001188</vgno>
    <barcode>2100118800009</barcode>
    <name>手撕餐包</name>
    <deptid>18211111</deptid>
    <spec />
    <unit>个</unit>
    <price>450</price>
    <type>0</type>
    <x>1</x>
    <ptype>n</ptype>
    <prodtype>0</prodtype>
    <pknum>1</pknum>
  </goods>
  <goods>
    <vgno>001191</vgno>
    <barcode>2100119100009</barcode>
    <name>加洲提子方包</name>
    <deptid>18211111</deptid>
    <spec />
    <unit>个</unit>
    <price>600</price>
    <type>0</type>
    <x>1</x>
    <ptype>n</ptype>
    <prodtype>0</prodtype>
    <pknum>1</pknum>
  </goods>
  <goods>
    <vgno>001193</vgno>
    <barcode>2100119300003</barcode>
    <name>白方包</name>
    <deptid>18211111</deptid>
    <spec />
    <unit>个</unit>
    <price>550</price>
    <type>0</type>
    <x>1</x>
    <ptype>n</ptype>
    <prodtype>0</prodtype>
    <pknum>1</pknum>
  </goods>
  <goods>
    <vgno>001195</vgno>
    <barcode>2100119500007</barcode>
    <name>日式芝士蛋糕(小)</name>
    <deptid>19711111</deptid>
    <spec />
    <unit>个</unit>
    <price>800</price>
    <type>0</type>
    <x>1</x>
    <ptype>n</ptype>
    <prodtype>0</prodtype>
    <pknum>1</pknum>
  </goods>
  <goods>
    <vgno>001410</vgno>
    <barcode>2100141000001</barcode>
    <name>加州阳光提子蛋糕</name>
    <deptid>19211111</deptid>
    <spec />
    <unit>个</unit>
    <price>500</price>
    <type>0</type>
    <x>1</x>
    <ptype>n</ptype>
    <prodtype>0</prodtype>
    <pknum>1</pknum>
  </goods>
  <goods>
    <vgno>001529</vgno>
    <barcode>2100152900000</barcode>
    <name>手撕丹麦包</name>
    <deptid>18211111</deptid>
    <spec>1</spec>
    <unit>包</unit>
    <price>850</price>
    <type>0</type>
    <x>1</x>
    <ptype>n</ptype>
    <prodtype>0</prodtype>
    <pknum>1</pknum>
  </goods>
  <goods>
    <vgno>001530</vgno>
    <barcode>2100153000006</barcode>
    <name>富士山</name>
    <deptid>18111111</deptid>
    <spec>1</spec>
    <unit>包</unit>
    <price>350</price>
    <type>0</type>
    <x>1</x>
    <ptype>n</ptype>
    <prodtype>0</prodtype>
    <pknum>1</pknum>
  </goods>
  <goods>
    <vgno>001535</vgno>
    <barcode>2100153500001</barcode>
    <name>千层吐司</name>
    <deptid>18211111</deptid>
    <spec>1</spec>
    <unit>包</unit>
    <price>650</price>
    <type>0</type>
    <x>1</x>
    <ptype>n</ptype>
    <prodtype>0</prodtype>
    <pknum>1</pknum>
  </goods>
  <goods>
    <vgno>001537</vgno>
    <barcode>2100153700005</barcode>
    <name>日式红豆包</name>
    <deptid>18111111</deptid>
    <spec>1</spec>
    <unit>包</unit>
    <price>300</price>
    <type>0</type>
    <x>1</x>
    <ptype>n</ptype>
    <prodtype>0</prodtype>
    <pknum>1</pknum>
  </goods>
  <goods>
    <vgno>001538</vgno>
    <barcode>2100153800002</barcode>
    <name>香橙千层包</name>
    <deptid>18111111</deptid>
    <spec>1</spec>
    <unit>包</unit>
    <price>400</price>
    <type>0</type>
    <x>1</x>
    <ptype>n</ptype>
    <prodtype>0</prodtype>
    <pknum>1</pknum>
  </goods>
  <goods>
    <vgno>001655</vgno>
    <barcode>2100165500006</barcode>
    <name>荣华大礼</name>
    <deptid>08111111</deptid>
    <spec>1</spec>
    <unit>箱</unit>
    <price>69600</price>
    <type>0</type>
    <x>1</x>
    <ptype>n</ptype>
    <prodtype>0</prodtype>
    <pknum>1</pknum>
  </goods>
  <goods>
    <vgno>001656</vgno>
    <barcode>2100165600003</barcode>
    <name>荣华有礼(大装)</name>
    <deptid>08111111</deptid>
    <spec>1</spec>
    <unit>箱</unit>
    <price>21800</price>
    <type>0</type>
    <x>1</x>
    <ptype>n</ptype>
    <prodtype>0</prodtype>
    <pknum>1</pknum>
  </goods>
  <goods>
    <vgno>001657</vgno>
    <barcode>2100165700000</barcode>
    <name>荣华有礼</name>
    <deptid>08111111</deptid>
    <spec>1</spec>
    <unit>箱</unit>
    <price>12700</price>
    <type>0</type>
    <x>1</x>
    <ptype>n</ptype>
    <prodtype>0</prodtype>
    <pknum>1</pknum>
  </goods>
  <goods>
    <vgno>001681</vgno>
    <barcode>2100168100005</barcode>
    <name>牛角酥包</name>
    <deptid>18211111</deptid>
    <spec>65g</spec>
    <unit>包</unit>
    <price>500</price>
    <type>0</type>
    <x>1</x>
    <ptype>n</ptype>
    <prodtype>0</prodtype>
    <pknum>1</pknum>
  </goods>
  <goods>
    <vgno>001785</vgno>
    <barcode>2100178500000</barcode>
    <name>乡村吐司</name>
    <deptid>18211111</deptid>
    <spec>160g</spec>
    <unit>包</unit>
    <price>600</price>
    <type>0</type>
    <x>1</x>
    <ptype>n</ptype>
    <prodtype>0</prodtype>
    <pknum>1</pknum>
  </goods>
  <goods>
    <vgno>001822</vgno>
    <barcode>2100182200002</barcode>
    <name>菠萝鲜油包</name>
    <deptid>18111111</deptid>
    <spec />
    <unit>个</unit>
    <price>450</price>
    <type>0</type>
    <x>1</x>
    <ptype>n</ptype>
    <prodtype>0</prodtype>
    <pknum>1</pknum>
  </goods>
  <goods>
    <vgno>001825</vgno>
    <barcode>2100182500003</barcode>
    <name>轻乳酪提子蛋糕面包</name>
    <deptid>18111111</deptid>
    <spec />
    <unit>个</unit>
    <price>300</price>
    <type>0</type>
    <x>1</x>
    <ptype>n</ptype>
    <prodtype>0</prodtype>
    <pknum>1</pknum>
  </goods>
  <goods>
    <vgno>001826</vgno>
    <barcode>2100182600000</barcode>
    <name>牛奶芝麻小卷卷</name>
    <deptid>18111111</deptid>
    <spec />
    <unit>个</unit>
    <price>200</price>
    <type>0</type>
    <x>1</x>
    <ptype>n</ptype>
    <prodtype>0</prodtype>
    <pknum>1</pknum>
  </goods>
  <goods>
    <vgno>001828</vgno>
    <barcode>2100182800004</barcode>
    <name>美味培根小甜包</name>
    <deptid>18111111</deptid>
    <spec />
    <unit>个</unit>
    <price>400</price>
    <type>0</type>
    <x>1</x>
    <ptype>n</ptype>
    <prodtype>0</prodtype>
    <pknum>1</pknum>
  </goods>
  <goods>
    <vgno>001933</vgno>
    <barcode>2100193300005</barcode>
    <name>荣华蜂蜜黄皮(瓶装)</name>
    <deptid>03332212</deptid>
    <spec>60g</spec>
    <unit>瓶</unit>
    <price>700</price>
    <type>0</type>
    <x>1</x>
    <ptype>n</ptype>
    <prodtype>0</prodtype>
    <pknum>1</pknum>
  </goods>
  <goods>
    <vgno>001934</vgno>
    <barcode>2100193400002</barcode>
    <name>荣华玫瑰花(瓶装)</name>
    <deptid>03332212</deptid>
    <spec>80g</spec>
    <unit>瓶</unit>
    <price>700</price>
    <type>0</type>
    <x>1</x>
    <ptype>n</ptype>
    <prodtype>0</prodtype>
    <pknum>1</pknum>
  </goods>
  <goods>
    <vgno>001935</vgno>
    <barcode>2100193500009</barcode>
    <name>荣华甘草榄(瓶装)</name>
    <deptid>03332212</deptid>
    <spec>100g</spec>
    <unit>瓶</unit>
    <price>700</price>
    <type>0</type>
    <x>1</x>
    <ptype>n</ptype>
    <prodtype>0</prodtype>
    <pknum>1</pknum>
  </goods>
  <goods>
    <vgno>001936</vgno>
    <barcode>2100193600006</barcode>
    <name>荣华甘草榄(袋装)</name>
    <deptid>03332212</deptid>
    <spec>150g</spec>
    <unit>袋</unit>
    <price>1050</price>
    <type>0</type>
    <x>1</x>
    <ptype>n</ptype>
    <prodtype>0</prodtype>
    <pknum>1</pknum>
  </goods>
  <goods>
    <vgno>001937</vgno>
    <barcode>2100193700003</barcode>
    <name>荣华话梅(瓶装)</name>
    <deptid>03332212</deptid>
    <spec>80g</spec>
    <unit>瓶</unit>
    <price>950</price>
    <type>0</type>
    <x>1</x>
    <ptype>n</ptype>
    <prodtype>0</prodtype>
    <pknum>1</pknum>
  </goods>
  <goods>
    <vgno>001938</vgno>
    <barcode>2100193800000</barcode>
    <name>荣华原色仁?(瓶装)</name>
    <deptid>03332212</deptid>
    <spec>160g</spec>
    <unit>瓶</unit>
    <price>1500</price>
    <type>0</type>
    <x>1</x>
    <ptype>n</ptype>
    <prodtype>0</prodtype>
    <pknum>1</pknum>
  </goods>
  <goods>
    <vgno>001939</vgno>
    <barcode>2100193900007</barcode>
    <name>荣华乌梅王(瓶装)</name>
    <deptid>03332212</deptid>
    <spec>200g</spec>
    <unit>瓶</unit>
    <price>1500</price>
    <type>0</type>
    <x>1</x>
    <ptype>n</ptype>
    <prodtype>0</prodtype>
    <pknum>1</pknum>
  </goods>
  <goods>
    <vgno>001940</vgno>
    <barcode>2100194000003</barcode>
    <name>荣华乌梅王(袋装)</name>
    <deptid>03332212</deptid>
    <spec>170g</spec>
    <unit>袋</unit>
    <price>1500</price>
    <type>0</type>
    <x>1</x>
    <ptype>n</ptype>
    <prodtype>0</prodtype>
    <pknum>1</pknum>
  </goods>
  <goods>
    <vgno>001941</vgno>
    <barcode>2100194100000</barcode>
    <name>荣华香话桃(瓶装)</name>
    <deptid>03332212</deptid>
    <spec>330g</spec>
    <unit>瓶</unit>
    <price>2000</price>
    <type>0</type>
    <x>1</x>
    <ptype>n</ptype>
    <prodtype>0</prodtype>
    <pknum>1</pknum>
  </goods>
  <goods>
    <vgno>001942</vgno>
    <barcode>2100194200007</barcode>
    <name>荣华香话桃(袋装)</name>
    <deptid>03332212</deptid>
    <spec>150g</spec>
    <unit>袋</unit>
    <price>1400</price>
    <type>0</type>
    <x>1</x>
    <ptype>n</ptype>
    <prodtype>0</prodtype>
    <pknum>1</pknum>
  </goods>
  <goods>
    <vgno>001943</vgno>
    <barcode>2100194300004</barcode>
    <name>荣华红瓜子(袋装)</name>
    <deptid>03332212</deptid>
    <spec>300g</spec>
    <unit>袋</unit>
    <price>2400</price>
    <type>0</type>
    <x>1</x>
    <ptype>n</ptype>
    <prodtype>0</prodtype>
    <pknum>1</pknum>
  </goods>
  <goods>
    <vgno>001944</vgno>
    <barcode>2100194400001</barcode>
    <name>荣华黑瓜子(袋装)</name>
    <deptid>03332212</deptid>
    <spec>300g</spec>
    <unit>袋</unit>
    <price>1900</price>
    <type>0</type>
    <x>1</x>
    <ptype>n</ptype>
    <prodtype>0</prodtype>
    <pknum>1</pknum>
  </goods>
  <goods>
    <vgno>001945</vgno>
    <barcode>2100194500008</barcode>
    <name>荣华花生(袋装)</name>
    <deptid>03332212</deptid>
    <spec>220g</spec>
    <unit>袋</unit>
    <price>1100</price>
    <type>0</type>
    <x>1</x>
    <ptype>n</ptype>
    <prodtype>0</prodtype>
    <pknum>1</pknum>
  </goods>
  <goods>
    <vgno>001946</vgno>
    <barcode>2100194600005</barcode>
    <name>荣华爽青梅(瓶装)</name>
    <deptid>03332212</deptid>
    <spec />
    <unit>瓶</unit>
    <price>2000</price>
    <type>0</type>
    <x>1</x>
    <ptype>n</ptype>
    <prodtype>0</prodtype>
    <pknum>1</pknum>
  </goods>
  <goods>
    <vgno>001947</vgno>
    <barcode>2100194700002</barcode>
    <name>荣华爽青梅(袋装)</name>
    <deptid>03332212</deptid>
    <spec />
    <unit>袋</unit>
    <price>1400</price>
    <type>0</type>
    <x>1</x>
    <ptype>n</ptype>
    <prodtype>0</prodtype>
    <pknum>1</pknum>
  </goods>
  <goods>
    <vgno>001948</vgno>
    <barcode>2100194800009</barcode>
    <name>荣华黑加仑(瓶装)</name>
    <deptid>03332212</deptid>
    <spec />
    <unit>瓶</unit>
    <price>2300</price>
    <type>0</type>
    <x>1</x>
    <ptype>n</ptype>
    <prodtype>0</prodtype>
    <pknum>1</pknum>
  </goods>
  <goods>
    <vgno>001949</vgno>
    <barcode>2100194900006</barcode>
    <name>荣华陈皮梅(袋装)</name>
    <deptid>03332212</deptid>
    <spec />
    <unit>袋</unit>
    <price>1550</price>
    <type>0</type>
    <x>1</x>
    <ptype>n</ptype>
    <prodtype>0</prodtype>
    <pknum>1</pknum>
  </goods>
  <goods>
    <vgno>001950</vgno>
    <barcode>2100195000002</barcode>
    <name>荣华雪花应子(袋装)</name>
    <deptid>03332212</deptid>
    <spec />
    <unit>袋</unit>
    <price>1550</price>
    <type>0</type>
    <x>1</x>
    <ptype>n</ptype>
    <prodtype>0</prodtype>
    <pknum>1</pknum>
  </goods>
  <goods>
    <vgno>002111</vgno>
    <barcode>2100211100006</barcode>
    <name>全麦核桃小餐包</name>
    <deptid>18211111</deptid>
    <spec />
    <unit>包</unit>
    <price>750</price>
    <type>0</type>
    <x>1</x>
    <ptype>n</ptype>
    <prodtype>0</prodtype>
    <pknum>1</pknum>
  </goods>
  <goods>
    <vgno>002112</vgno>
    <barcode>2100211200003</barcode>
    <name>提子小甜包</name>
    <deptid>18211111</deptid>
    <spec />
    <unit>包</unit>
    <price>450</price>
    <type>0</type>
    <x>1</x>
    <ptype>n</ptype>
    <prodtype>0</prodtype>
    <pknum>1</pknum>
  </goods>
  <goods>
    <vgno>002113</vgno>
    <barcode>2100211300000</barcode>
    <name>奶油粟米条</name>
    <deptid>18211111</deptid>
    <spec />
    <unit>包</unit>
    <price>600</price>
    <type>0</type>
    <x>1</x>
    <ptype>n</ptype>
    <prodtype>0</prodtype>
    <pknum>1</pknum>
  </goods>
  <goods>
    <vgno>002114</vgno>
    <barcode>2100211400007</barcode>
    <name>原味雪芳蛋糕</name>
    <deptid>19711111</deptid>
    <spec />
    <unit>包</unit>
    <price>300</price>
    <type>0</type>
    <x>1</x>
    <ptype>n</ptype>
    <prodtype>0</prodtype>
    <pknum>1</pknum>
  </goods>
  <goods>
    <vgno>002115</vgno>
    <barcode>2100211500004</barcode>
    <name>巧克力味雪芳蛋糕</name>
    <deptid>19711111</deptid>
    <spec />
    <unit>包</unit>
    <price>300</price>
    <type>0</type>
    <x>1</x>
    <ptype>n</ptype>
    <prodtype>0</prodtype>
    <pknum>1</pknum>
  </goods>
  <goods>
    <vgno>002116</vgno>
    <barcode>2100211600001</barcode>
    <name>绿茶味雪芳蛋糕</name>
    <deptid>19711111</deptid>
    <spec />
    <unit>包</unit>
    <price>450</price>
    <type>0</type>
    <x>1</x>
    <ptype>n</ptype>
    <prodtype>0</prodtype>
    <pknum>1</pknum>
  </goods>
  <goods>
    <vgno>002189</vgno>
    <barcode>2100218900005</barcode>
    <name>黑芝麻蜂蜜吐司</name>
    <deptid>18211111</deptid>
    <spec />
    <unit>包</unit>
    <price>450</price>
    <type>0</type>
    <x>1</x>
    <ptype>n</ptype>
    <prodtype>0</prodtype>
    <pknum>1</pknum>
  </goods>
  <goods>
    <vgno>002190</vgno>
    <barcode>2100219000001</barcode>
    <name>紫米红蜜豆吐司</name>
    <deptid>18211111</deptid>
    <spec />
    <unit>包</unit>
    <price>450</price>
    <type>0</type>
    <x>1</x>
    <ptype>n</ptype>
    <prodtype>0</prodtype>
    <pknum>1</pknum>
  </goods>
  <goods>
    <vgno>002221</vgno>
    <barcode>2100222100002</barcode>
    <name>芝士蛋肉松三文治</name>
    <deptid>18111111</deptid>
    <spec />
    <unit>个</unit>
    <price>800</price>
    <type>0</type>
    <x>1</x>
    <ptype>n</ptype>
    <prodtype>0</prodtype>
    <pknum>1</pknum>
  </goods>
  <goods>
    <vgno>002222</vgno>
    <barcode>2100222200009</barcode>
    <name>火腿蛋肉松三文治</name>
    <deptid>18111111</deptid>
    <spec />
    <unit>个</unit>
    <price>800</price>
    <type>0</type>
    <x>1</x>
    <ptype>n</ptype>
    <prodtype>0</prodtype>
    <pknum>1</pknum>
  </goods>
  <goods>
    <vgno>002257</vgno>
    <barcode>2100225700001</barcode>
    <name>魔法圣诞屋</name>
    <deptid>19111111</deptid>
    <spec />
    <unit>个</unit>
    <price>8800</price>
    <type>0</type>
    <x>1</x>
    <ptype>n</ptype>
    <prodtype>0</prodtype>
    <pknum>1</pknum>
  </goods>
  <goods>
    <vgno>002403</vgno>
    <barcode>2100240300002</barcode>
    <name>甜餐包</name>
    <deptid>18211111</deptid>
    <spec />
    <unit>个</unit>
    <price>550</price>
    <type>0</type>
    <x>1</x>
    <ptype>n</ptype>
    <prodtype>0</prodtype>
    <pknum>1</pknum>
  </goods>
  <goods>
    <vgno>001447</vgno>
    <barcode>600003694614</barcode>
    <name>四式杂粮小法包</name>
    <deptid>18211111</deptid>
    <spec>80G</spec>
    <unit>包</unit>
    <price>550</price>
    <type>0</type>
    <x>1</x>
    <ptype>n</ptype>
    <prodtype>0</prodtype>
    <pknum>1</pknum>
  </goods>
  <goods>
    <vgno>001448</vgno>
    <barcode>600003694615</barcode>
    <name>杂粮软心包</name>
    <deptid>18111111</deptid>
    <spec>60G</spec>
    <unit>包</unit>
    <price>350</price>
    <type>0</type>
    <x>1</x>
    <ptype>n</ptype>
    <prodtype>0</prodtype>
    <pknum>1</pknum>
  </goods>
  <goods>
    <vgno>000032</vgno>
    <barcode>6920671201084</barcode>
    <name>鸡仔饼 110g</name>
    <deptid>23111111</deptid>
    <spec>110g</spec>
    <unit>包</unit>
    <price>700</price>
    <type>0</type>
    <x>1</x>
    <ptype>n</ptype>
    <prodtype>0</prodtype>
    <pknum>1</pknum>
  </goods>
  <goods>
    <vgno>000014</vgno>
    <barcode>6920671202357</barcode>
    <name>传世国饼</name>
    <deptid>02322133</deptid>
    <spec>740g</spec>
    <unit>盒</unit>
    <price>32800</price>
    <type>0</type>
    <x>1</x>
    <ptype>n</ptype>
    <prodtype>0</prodtype>
    <pknum>1</pknum>
  </goods>
  <goods>
    <vgno>000026</vgno>
    <barcode>6920671280027</barcode>
    <name>芝麻薄脆</name>
    <deptid>08133213</deptid>
    <spec>100g</spec>
    <unit>盒</unit>
    <price>1600</price>
    <type>0</type>
    <x>1</x>
    <ptype>n</ptype>
    <prodtype>0</prodtype>
    <pknum>1</pknum>
  </goods>
  <goods>
    <vgno>000858</vgno>
    <barcode>6920671280041</barcode>
    <name>紫菜粒粒杏仁饼</name>
    <deptid>08133213</deptid>
    <spec>170g</spec>
    <unit>盒</unit>
    <price>1600</price>
    <type>0</type>
    <x>1</x>
    <ptype>n</ptype>
    <prodtype>0</prodtype>
    <pknum>1</pknum>
  </goods>
  <goods>
    <vgno>000857</vgno>
    <barcode>6920671280058</barcode>
    <name>原味粒粒杏仁饼</name>
    <deptid>08133213</deptid>
    <spec>170g</spec>
    <unit>盒</unit>
    <price>1600</price>
    <type>0</type>
    <x>1</x>
    <ptype>n</ptype>
    <prodtype>0</prodtype>
    <pknum>1</pknum>
  </goods>
  <goods>
    <vgno>000854</vgno>
    <barcode>6920671280065</barcode>
    <name>肉松粒粒杏仁饼</name>
    <deptid>08133213</deptid>
    <spec>170g</spec>
    <unit>盒</unit>
    <price>1600</price>
    <type>0</type>
    <x>1</x>
    <ptype>n</ptype>
    <prodtype>0</prodtype>
    <pknum>1</pknum>
  </goods>
  <goods>
    <vgno>000855</vgno>
    <barcode>6920671280072</barcode>
    <name>黑芝麻粒粒杏仁饼</name>
    <deptid>08133213</deptid>
    <spec>170g</spec>
    <unit>盒</unit>
    <price>1600</price>
    <type>0</type>
    <x>1</x>
    <ptype>n</ptype>
    <prodtype>0</prodtype>
    <pknum>1</pknum>
  </goods>
  <goods>
    <vgno>000853</vgno>
    <barcode>6920671280089</barcode>
    <name>小桃酥</name>
    <deptid>08133213</deptid>
    <spec>170g</spec>
    <unit>盒</unit>
    <price>1600</price>
    <type>0</type>
    <x>1</x>
    <ptype>n</ptype>
    <prodtype>0</prodtype>
    <pknum>1</pknum>
  </goods>
  <goods>
    <vgno>000030</vgno>
    <barcode>6920671280096</barcode>
    <name>香葱南乳旋风圈</name>
    <deptid>08133213</deptid>
    <spec>85g</spec>
    <unit>盒</unit>
    <price>1600</price>
    <type>0</type>
    <x>1</x>
    <ptype>n</ptype>
    <prodtype>0</prodtype>
    <pknum>1</pknum>
  </goods>
  <goods>
    <vgno>000084</vgno>
    <barcode>6920671280102</barcode>
    <name>手卷肉松烤肠</name>
    <deptid>08111111</deptid>
    <spec>138g</spec>
    <unit>盒</unit>
    <price>1600</price>
    <type>0</type>
    <x>1</x>
    <ptype>n</ptype>
    <prodtype>0</prodtype>
    <pknum>1</pknum>
  </goods>
  <goods>
    <vgno>000427</vgno>
    <barcode>6923959020469</barcode>
    <name>鲜牛油排包</name>
    <deptid>18211111</deptid>
    <spec>280g</spec>
    <unit>包</unit>
    <price>850</price>
    <type>0</type>
    <x>1</x>
    <ptype>n</ptype>
    <prodtype>0</prodtype>
    <pknum>1</pknum>
  </goods>
  <goods>
    <vgno>000371</vgno>
    <barcode>6923959020582</barcode>
    <name>餐蛋肉松包</name>
    <deptid>18111111</deptid>
    <spec>85g</spec>
    <unit>个</unit>
    <price>500</price>
    <type>0</type>
    <x>1</x>
    <ptype>n</ptype>
    <prodtype>0</prodtype>
    <pknum>1</pknum>
  </goods>
  <goods>
    <vgno>000375</vgno>
    <barcode>6923959020629</barcode>
    <name>叉烧包</name>
    <deptid>18111111</deptid>
    <spec>85g</spec>
    <unit>个</unit>
    <price>450</price>
    <type>0</type>
    <x>1</x>
    <ptype>n</ptype>
    <prodtype>0</prodtype>
    <pknum>1</pknum>
  </goods>
  <goods>
    <vgno>000376</vgno>
    <barcode>6923959020636</barcode>
    <name>肉松包</name>
    <deptid>18111111</deptid>
    <spec>85g</spec>
    <unit>个</unit>
    <price>400</price>
    <type>0</type>
    <x>1</x>
    <ptype>n</ptype>
    <prodtype>0</prodtype>
    <pknum>1</pknum>
  </goods>
  <goods>
    <vgno>000378</vgno>
    <barcode>6923959020667</barcode>
    <name>?宝脆肠</name>
    <deptid>18111111</deptid>
    <spec>85g</spec>
    <unit>个</unit>
    <price>350</price>
    <type>0</type>
    <x>1</x>
    <ptype>n</ptype>
    <prodtype>0</prodtype>
    <pknum>1</pknum>
  </goods>
  <goods>
    <vgno>000399</vgno>
    <barcode>6923959020766</barcode>
    <name>鸡尾排包</name>
    <deptid>18211111</deptid>
    <spec>大</spec>
    <unit>个</unit>
    <price>750</price>
    <type>0</type>
    <x>1</x>
    <ptype>n</ptype>
    <prodtype>0</prodtype>
    <pknum>1</pknum>
  </goods>
  <goods>
    <vgno>000389</vgno>
    <barcode>6923959020834</barcode>
    <name>?宝芝士火腿</name>
    <deptid>18111111</deptid>
    <spec>85g</spec>
    <unit>个</unit>
    <price>350</price>
    <type>0</type>
    <x>1</x>
    <ptype>n</ptype>
    <prodtype>0</prodtype>
    <pknum>1</pknum>
  </goods>
  <goods>
    <vgno>000622</vgno>
    <barcode>6923959020971</barcode>
    <name>肠仔包</name>
    <deptid>18111111</deptid>
    <spec>85g</spec>
    <unit>个</unit>
    <price>380</price>
    <type>0</type>
    <x>1</x>
    <ptype>n</ptype>
    <prodtype>0</prodtype>
    <pknum>1</pknum>
  </goods>
  <goods>
    <vgno>000610</vgno>
    <barcode>6923959021107</barcode>
    <name>菠萝红豆包</name>
    <deptid>18111111</deptid>
    <spec>85g</spec>
    <unit>个</unit>
    <price>250</price>
    <type>0</type>
    <x>1</x>
    <ptype>n</ptype>
    <prodtype>0</prodtype>
    <pknum>1</pknum>
  </goods>
  <goods>
    <vgno>000712</vgno>
    <barcode>692395902130</barcode>
    <name>北印度咖哩鸡包</name>
    <deptid>18111111</deptid>
    <spec>85g</spec>
    <unit>个</unit>
    <price>350</price>
    <type>0</type>
    <x>1</x>
    <ptype>n</ptype>
    <prodtype>0</prodtype>
    <pknum>1</pknum>
  </goods>
  <goods>
    <vgno>000597</vgno>
    <barcode>6923959021305</barcode>
    <name>四色什果</name>
    <deptid>19211111</deptid>
    <spec>大</spec>
    <unit>件</unit>
    <price>350</price>
    <type>0</type>
    <x>1</x>
    <ptype>n</ptype>
    <prodtype>0</prodtype>
    <pknum>1</pknum>
  </goods>
  <goods>
    <vgno>000713</vgno>
    <barcode>692395902131</barcode>
    <name>蜜汁肠仔包</name>
    <deptid>18111111</deptid>
    <spec>95g</spec>
    <unit>个</unit>
    <price>350</price>
    <type>0</type>
    <x>1</x>
    <ptype>n</ptype>
    <prodtype>0</prodtype>
    <pknum>1</pknum>
  </goods>
  <goods>
    <vgno>000596</vgno>
    <barcode>6923959021312</barcode>
    <name>拿破仑朱古力</name>
    <deptid>19211111</deptid>
    <spec>大</spec>
    <unit>件</unit>
    <price>350</price>
    <type>0</type>
    <x>1</x>
    <ptype>n</ptype>
    <prodtype>0</prodtype>
    <pknum>1</pknum>
  </goods>
  <goods>
    <vgno>000714</vgno>
    <barcode>692395902132</barcode>
    <name>辣三文鱼松包</name>
    <deptid>18111111</deptid>
    <spec>65g</spec>
    <unit>个</unit>
    <price>350</price>
    <type>0</type>
    <x>1</x>
    <ptype>n</ptype>
    <prodtype>0</prodtype>
    <pknum>1</pknum>
  </goods>
  <goods>
    <vgno>000595</vgno>
    <barcode>6923959021329</barcode>
    <name>蓝莓蛋糕</name>
    <deptid>19211111</deptid>
    <spec>大</spec>
    <unit>件</unit>
    <price>350</price>
    <type>0</type>
    <x>1</x>
    <ptype>n</ptype>
    <prodtype>0</prodtype>
    <pknum>1</pknum>
  </goods>
  <goods>
    <vgno>000715</vgno>
    <barcode>692395902133</barcode>
    <name>芝士火腿香蒜包</name>
    <deptid>18111111</deptid>
    <spec>95g</spec>
    <unit>个</unit>
    <price>350</price>
    <type>0</type>
    <x>1</x>
    <ptype>n</ptype>
    <prodtype>0</prodtype>
    <pknum>1</pknum>
  </goods>
  <goods>
    <vgno>000594</vgno>
    <barcode>6923959021336</barcode>
    <name>香橙咖啡</name>
    <deptid>19211111</deptid>
    <spec>大</spec>
    <unit>件</unit>
    <price>350</price>
    <type>0</type>
    <x>1</x>
    <ptype>n</ptype>
    <prodtype>0</prodtype>
    <pknum>1</pknum>
  </goods>
  <goods>
    <vgno>002421</vgno>
    <barcode>6941409800621</barcode>
    <name>家家送传世国饼</name>
    <deptid>02213133</deptid>
    <spec />
    <unit>盒</unit>
    <price>32800</price>
    <type>0</type>
    <x>1</x>
    <ptype>n</ptype>
    <prodtype>0</prodtype>
    <pknum>1</pknum>
  </goods>
  <goods>
    <vgno>000610</vgno>
    <barcode>6949017210160</barcode>
    <name>菠萝红豆包</name>
    <deptid>18111111</deptid>
    <spec>85g</spec>
    <unit>个</unit>
    <price>250</price>
    <type>0</type>
    <x>1</x>
    <ptype>n</ptype>
    <prodtype>0</prodtype>
    <pknum>1</pknum>
  </goods>
  <goods>
    <vgno>001797</vgno>
    <barcode>6949017210887</barcode>
    <name>鲜油脆香片</name>
    <deptid>18211111</deptid>
    <spec>135g</spec>
    <unit>个</unit>
    <price>450</price>
    <type>0</type>
    <x>1</x>
    <ptype>n</ptype>
    <prodtype>0</prodtype>
    <pknum>1</pknum>
  </goods>
  <goods>
    <vgno>000081</vgno>
    <barcode>9955678100310</barcode>
    <name>荣华榄仁合桃酥</name>
    <deptid>05132113</deptid>
    <spec>150g</spec>
    <unit>个</unit>
    <price>700</price>
    <type>0</type>
    <x>1</x>
    <ptype>n</ptype>
    <prodtype>0</prodtype>
    <pknum>1</pknum>
  </goods>
</goodsExtList>

